git2vec/__init__.py
git2vec/loader.py
git2vec/vectordb.py
git2vec-0.1.8.dist-info/METADATA
git2vec-0.1.8.dist-info/WHEEL
git2vec-0.1.8.dist-info/top_level.txt
git2vec-0.1.8.dist-info/RECORD
