Metadata-Version: 2.1
Name: git2vec
Version: 0.1.8
Summary: A useful module for handling Git data.
Home-page: https://github.com/voynow/git2vec
Author: Jamie Voynow
Author-email: voynow99@gmail.com
Classifier: Development Status :: 3 - Alpha
Classifier: Intended Audience :: Developers
Classifier: Topic :: Software Development :: Build Tools
Classifier: License :: OSI Approved :: MIT License
Classifier: Programming Language :: Python :: 3.6
Classifier: Programming Language :: Python :: 3.7
Classifier: Programming Language :: Python :: 3.8
Classifier: Programming Language :: Python :: 3.9
Requires-Dist: langchain
Requires-Dist: pinecone-client
Requires-Dist: tiktoken
Requires-Dist: gitpython
Requires-Dist: python-dotenv
Requires-Dist: pandas
